dockerman/__init__.py
dockerman/__main__.py
dockerman/base.py
dockerman/container.py
dockerman/image.py
dockerman/main.py
dockerman/utils.py
dockerman/tests/__init__.py
dockerman/tests/test_container.py
dockerman/tests/test_main.py
dockerman/tests/test_utils.py
dockerman-0.1.2.dist-info/DESCRIPTION.rst
dockerman-0.1.2.dist-info/METADATA
dockerman-0.1.2.dist-info/RECORD
dockerman-0.1.2.dist-info/WHEEL
dockerman-0.1.2.dist-info/entry_points.txt
dockerman-0.1.2.dist-info/metadata.json
dockerman-0.1.2.dist-info/top_level.txt
