Metadata-Version: 2.0
Name: dockerman
Version: 0.1.2
Summary: Manage docker images and docker containers used for local/desktop applications
Home-page: https://github.com/mbodenhamer/dockerman
Author: Matt Bodenhamer
Author-email: mbodenhamer@mbodenhamer.com
License: MIT
Keywords: docker,application
Platform: UNKNOWN
Classifier: Development Status :: 2 - Pre-Alpha
Classifier: Environment :: Console
Classifier: Intended Audience :: Developers
Classifier: Intended Audience :: System Administrators
Classifier: License :: OSI Approved :: MIT License
Classifier: Operating System :: POSIX :: Linux
Classifier: Programming Language :: Python
Classifier: Programming Language :: Python :: 2.7
Classifier: Programming Language :: Python :: 3.6
Classifier: Topic :: Utilities
Requires-Dist: docker
Requires-Dist: syn (>=0.0.14)
Requires-Dist: syn.utils
